{"name":"shouldInterpretingBasedOn","testCaseName":"WhenInterpretingInstructions","userStory":{"id":"WhenInterpretingInstructions","storyName":"When interpreting instructions","storyClassName":"WhenInterpretingInstructions","path":"","type":"story"},"featureTag":{"name":"When interpreting instructions","type":"story"},"title":"Should interpreting based on","tags":[{"name":"When interpreting instructions","type":"story"}],"startTime":1525854553614,"duration":281,"manual":false,"testSource":"JUnit","result":"SUCCESS"}